tree_sitter_sparql/__init__.py
tree_sitter_sparql/__init__.pyi
tree_sitter_sparql/binding.cpython-312-aarch64-linux-gnu.so
tree_sitter_sparql/py.typed
tree_sitter_sparql-0.1.0.dist-info/METADATA
tree_sitter_sparql-0.1.0.dist-info/WHEEL
tree_sitter_sparql-0.1.0.dist-info/top_level.txt
tree_sitter_sparql-0.1.0.dist-info/RECORD
tree_sitter_sparql-0.1.0.dist-info/licenses/LICENSE
