Metadata-Version: 2.4
Name: tree-sitter-sparql
Version: 0.1.0
Summary: SPARQL grammar for tree-sitter
Author-email: Etienne Posthumus <ep@epoz.org>
License-Expression: MIT
Project-URL: Homepage, https://github.com/epoz/tree_sitter_sparql
Keywords: tree-sitter,sparql,parser,incremental
Requires-Python: >=3.8
License-File: LICENSE
Requires-Dist: tree-sitter>=0.21.3
Dynamic: license-file
